{"status": {"state": "up", "reason": "user-set"}, "vendor": {}, "addresses": {"ipv4": "124.34.217.124"}, "tcp": {"80": {"product": "", "state": "open", "version": "", "name": "http", "conf": "3", "extrainfo": "", "reason": "syn-ack", "cpe": ""}, "443": {"product": "", "state": "closed", "version": "", "name": "https", "conf": "3", "extrainfo": "", "reason": "conn-refused", "cpe": ""}}, "datetime": "2016-10-04 21:04:40.144763", "hostnames": [{"type": "user", "name": "www.efyo2gctw42.com"}, {"type": "PTR", "name": "2f.9s.com"}]}